asyncpgx/__init__.py
asyncpgx/client.py
asyncpgx/connection.py
asyncpgx/commands/__init__.py
asyncpgx/commands/decr.py
asyncpgx/commands/delete.py
asyncpgx/commands/exists.py
asyncpgx/commands/expire.py
asyncpgx/commands/flushall.py
asyncpgx/commands/get.py
asyncpgx/commands/incr.py
asyncpgx/commands/keys.py
asyncpgx/commands/set.py
asyncpgx/commands/ttl.py
asyncpgx/utils/__init__.py
asyncpgx/utils/patterns.py
asyncpgx/utils/schema.py
asyncpgx/utils/serialization.py
PyAsyncPGX-1.0.0.dist-info/METADATA
PyAsyncPGX-1.0.0.dist-info/WHEEL
PyAsyncPGX-1.0.0.dist-info/top_level.txt
PyAsyncPGX-1.0.0.dist-info/RECORD
